funny.pyc (Python 3.13)
[Code]
    File Name: chal.py
    Object Name: <module>
    Qualified Name: <module>
    Arg Count: 0
    Pos Only Arg Count: 0
    KW Only Arg Count: 0
    Stack Size: 7
    Flags: 0x00000000
    [Names]
        'Crypto.Cipher'
        'AES'
        'Crypto.Util.Padding'
        'pad'
        'unpad'
        'ImportError'
        'print'
        'exit'
        'a'
        'b'
        'c'
        'd'
        'e'
        'f'
        'g'
        'h'
        'i'
        'j'
        'k'
        'l'
        'm'
        'n'
        'o'
        'p'
        'q'
        'r'
        's'
        't'
        'u'
        'v'
        'w'
        'x'
        'y'
        'z'
        'input'
        'encode'
        'key'
        'iv'
        'len'
        'new'
        'MODE_CBC'
        'decrypt'
        'block_size'
        'decrypted'
        'decode'
        'i_wonder_what_this_decrypts_to'
    [Locals+Names]
    [Constants]
        0
        (
            'AES'
        )
        (
            'pad'
            'unpad'
        )
        'run `pip install pycryptodome` to be able to play this challenge'
        'Key > '
        'IV  > '
        32
        16
        b'\x1fQer\xec\xb6\x05\xee\xc0g/\x82\x0c\xdb\xecZ\x13\xf8\x08\x01\tB:\xe4\xbdkb/r\xba\xf6\xc0\xe9\xe6M\xf7\xa1\x02&\x17p\x7f)\xb4\xe0\xdf\xe8w'
        b'INTIGRITI'
        'gg'
        b'\xc0\xae\x13\x8a\xbb\x0b\xa1\x95\xf9\x8a\xe0\\\xb6\xc8\xd2\x1fHF*\x0bK\x11\xf2\x82\xfcIk\xd2|\xcdf\xd6@c\x17\xe9\xcc\xdd\x98O\xa5;=<\xea\\\x91\xf2\xc0I\x901)\x8bH\xab\xda}g\x95\x0f#<YN\x03\x94n\xd1\xed\xcf\x9a\xc4\xefU\x99\x92\xe7\xf0&^\xd9\xb9\xc7U\x7f\xce\x0eQ;9dU\xf2\x88\x17\xe2\xc0Q\x93&\xeb\x1f\xf9\'"$\x08?\x83~\xb1\xc8HK\x07\xce\xb2\x10\xd1\x9d\x99k\xba)X\xc5\x08\xec\xe7]\x81s\x9b\xdfsl\xad\xbc 8TM\xd9\xa1em;\xec\x03E\xa5EJ\xbaT:\'\xa3\xa9\xf4\xa9\x0b\xadL\xaer\xf1\x84\x02bI\xe3Ym-&\xb6\xae\\c\xa0\xbcJ@\xaf\xf9\x1d\x8bY\xa3\xa5\xe5b\xf3\xf1\x99b\xf2~\xbd\xf3\xd6\xf5m,\x82=u\x98G\x1b\x86s6\xcb\xf8x\xa9\x16\xfc\xe35\xd8\xca\x17K\xa4\xc6\x04d:\xbaN \xed\x15`\x8f\xd1\xe1\xfdHhr\xbc\xb08V\xb8\x8d\x83\x8a\xf2\x8e{\xe0M\xffs=\xfb\x8d;\xdf\xdd\xc1\x0fm\xeb{\xb5\x9bm\x83\xe7\xf9\x91F\xc0C\xdfP\rG\xd6\xfa\xd7Lb\x8eA\xe4\x008\xf2\xad\xd8\x0f\x9d\xb8\xbfM@\xf4\xca\xf4\xb2\xbbi\x0c\xff\x0fu\x9cT\x0b\xf8\x8e\x9c\x1e\xca\xbc\xcd\xaaG\xd9\x17xp\xd1B7\x0f\xe0\x914\xf1\xdb\xeczH\xbbc\xde\xfcyGA/\xce\x86\x91\xec\xe5:\xc1\x03\x8d]\x90J^\xdc\xa9+\x03Xh\xc3\xe9\x1cDxd\x1b\x0fF\x1f\x99\x18\x8e9DA{\x80\xea\xcf\xb0\xeb\xb0K\x8f\xe4\x07\x1f\x8e\x04n\xb8t\xe9\x13R\xf39\xf1\x17\x05\xfb\x00\xf8\xca\xfa}K\xa6\x8e+\xd5\xa9\x04\xb9I\xab+w\x93\xa8\xfek\xd3\x8bJt\xe3\xfea\xa1 \xb7\xb9\xae\x81\xe2:\xfc\x0b\x85\x15\xe4s\xef:xF\xd9\x83\xddi4\x9e6!\xc2\xbaP\\\xb4V6%\xc0"x\xd1\x15\xc1\x07\x10\xd0\xf9\x96\xee\xd6\xf1)\x9e\xe3\xb9\xe3T\xec\xdd\x8alF\x88\x101U\xed\xb8\xbcd\xfc\x02\xb3\xb4B\x04\xd4g\xc8\xc7\x83\x89^^\xc4\xfc\x02\xca\xcd\xb9\xa7\\|yU\xb71\xb4>\xa9\x1dxv4!\\\xe1\xc1\xe0?\xa3\xaf/(\x16\x0b\xcd\xd3\x99S\x0f\xe4\xfd\xa9\\\x17g\x9e\'N^\xca\x9f^\xec~G\xfa\xd9\xc5 R\xb1\x1f\x95\xaa\xe5:\xa7\x9f\xc2\x8bC\x88\xd2\xa1\xff\x83\x94a\x11J\xdb{\x1bb\x1aBs\x18\xef\xa7\xd7\x1e\xc3\xa4\xff\xa9v:M\xb2\xc59\x98\xe4f\x13!\xf5mz\xb1\x15\xdc\xf5x\xd3g\x0e%t\xda\x9aV\x0cQ\xe5Z{s5\xb1C\xe2!\xdf\xc4z\xaa9^/y\x01^\x99\xdb)4\x02,C\x16tQ\xa2Rj\x80f\xc5U\t\xbd\x1d\xaf/\xaf\x9b\x8cv\xd5\n\x0b\xf6$3\x97Ac\xd6\xff\xc0\x86\xe3\xe3\x1d\x87T\x1d\x8b\xab%S\x8a!\x9f\x1b\x9a$\xdb:\xf47\xa7,\x1cY\x9c*\xec\xcbt1\x9c\x9euGs\x18t\xf6\x81\xeb\xe0Dd\xedx\x02\xec"\xab\x80Bh\x03\xcb\x86\xe1*K\xa5O\xa3\xc2,q~\x87\x8a%\xcc%\x0c\xda-9F)\x00\x8b\xbe\x85\x17\xadl\xd2\xb0\x8c\x8e;U*\xfc4\xd6\r>\x04\xbe\x7f\x88\xc7T\xbd0\xa6\xe85\xa9.\x19\x8d\xfa%\x85\n\xe2\x84\xa8&\xcd\'\xb9\xd6\xebK\x8d\x10}\xc2\xd1\xde@9Uf\xa4_\xa2\xb9X\xd6;\xf9I\xcfc\xfc6\x94\xa5\x834\xbeBD\xfa\xfd\xb8.\x82\xfb)a\xf6L\x95V#\x05\xea}6\xe0C\xf7\xf4\xd3\xed\xba\x02v\xe5 \xcch,{\xad\xc7\xfc\xe1\xaf\xb3\x14R\xdb1\x07JK:g8\x8b\x9bw\x17\x1d\x13\x8ff\x8a\x0e\x98\xcd\xc4\xb1e^\x8c\xbai\x05\xa2\x9e\xc9\xd8{ D\x9c\x0f\xc1\x8a\x0b\x92\'\xed \x8f,\x00o\xa3\xb8%X\xa3\xde\xec\xfdu\x1a\xc9\xac\xfd\x1f\xf9<|\xd4G\x1a.\xac^\xfc\xc9I\x1fkG\xe9\xa1\x0e\xd2\x1b\x90\xb7\xfd\xd0.{\x00d6Y\x06\xcb,L\x9a\x82\xb5\xe6\x8f\xedp=\xbf\xbdFP\x88\xdf!\x0f}]\xecK\x0b3\x97f\xf6\'\x90\xe7\x9ex:xE\x9c\xe0\xbe\x14\xc8\x0f\xa3\xc8\xdag1\xe5{\xe1i|=\x14\x81wy\xb8W\xe7?j\x95;p\x1a\x95\xc7#6\xc3\x00\xec8\xae;\xc9\xf7\xcc\x0f\xb4K\x17w\x1f\xc9]\xa8D&\xb1\xacrs\xbeI\xc7\xab\xf29s\x85\xd7\xaf0\xb0|\x13\xa6\x96\x8f\xe2\x97\x84\x8ag\xf3\xb9ow!b\xa8\xd1\x83a[*$\x8a\xfdp\xc2\x7f\xb1f\xd4\x90z\xe3V\x16\xd8\xed\xa2@\n_\xb4\xd2)\xd4\x14\x85\xbay\xf65#3\xbf\x14\xbf\x1a\xb4\xcb\xd9\xc7\x0f\xe8\xa5!\xa0\xae\x00\x9a\xdb\xd8\xfbg\x8f\x99\xca&\x9f\xe7\x0c\xf3\x03\xd3rw\xe2P\x8c\x01\x0b\xa14-U\xb3\x8b?\x94\xfd\xed#\x99w4\xa2\xf7\xfaS\x10\xa5F\xcbY\x1a\xe7\x87I\xed\x02t,|\xb6c\x8f\xa4)\xa7\x8e\xe2\x18<\xaf\x05z g\xda\xa3\x19\xefq\xe4?\x92\xfdj+y}|\xc6\r}\xad\xd8\xecp\x96v\x8ah\x8b_\xec?\xfbpg\xc5\xfe\x9d=\x063\x17\x96\xe2>\xb1\xed-l\x95b\xb6\x81\xebF-\x1b\x12\xc2\x0b\xdeG\xbd\xdc\xe3\xf56u\xfd\x14\x17V\x8c\x87\x17_m?\xf7\xc3\xc2\xf0\x80;\x03\xea\xc9\xfd\x93~\xeff\x9b\xc5\r\x92\x9atb\xf9\x16\x8c&m4\xb5/F@\x12\')\xea\xff\x97\xf5C;\xd7\x08\xa0\xac`\xc5#\x8b\x80\t\xe4\xf1\x99\x81\xc9\xa7g\xe0\xb1\x02)CZVz\xa6\xcb\x84@!\x98\xf9n \xa0e.3\xa3I\xe8\xcd\x8a\x9d\xb6\xdf\x18G\xdd\xf8T6&\xaa\xde\xb6\x9d\xfb\xdb\x17\x00H\xe3Lm|\xc8\x80\xb0\x03\xd1\xd2\xaaw~\xa0\x00P\x1f\x1a_\x8b\t\x81\xc8p\xfa.\xfb\xd8;\x13\xbb\x80$\xe3\xa4\x05*\x91\x9eD$cc\xaf@\x9b\xaa\xb7&\xaf\x1a\xa1L/X\xc8\xafW\xa3\xb6\xd1\r\xa4\xe8\x91 ^4\xd4\xc7V7\xc6\xe4\x11\x12\xe0{x\x85\xbb\x92\x07\xc0\xd3\xec\xf2JcX\xdb\xcd\xda\xae\x80\xfa\x92\xae\xae&\x07\xaf\x86\xf8i\xabai\xed\x0c`'
        b'/\xa0\xaa<?\xb54q\xdb\x00\x8e\xfe w\xae\x89\xf3R3\xd7.\x83c\xe6\xb6E\xac|\xfd\x92\x95j'
        b'\x1fdu\xae\x8f\x9a\xa5\x8b,\x94\xa0T\xe5ib\xd0'
        None
    [Disassembly]
        0       RESUME                          0
        2       NOP                             
        4       LOAD_CONST                      0: 0
        6       LOAD_CONST                      1: ('AES',)
        8       IMPORT_NAME                     0: Crypto.Cipher
        10      IMPORT_FROM                     1: AES
        12      STORE_NAME                      1: AES
        14      POP_TOP                         
        16      LOAD_CONST                      0: 0
        18      LOAD_CONST                      2: ('pad', 'unpad')
        20      IMPORT_NAME                     2: Crypto.Util.Padding
        22      IMPORT_FROM                     3: pad
        24      STORE_NAME                      3: pad
        26      IMPORT_FROM                     4: unpad
        28      STORE_NAME                      4: unpad
        30      POP_TOP                         
        32      LOAD_CONST                      0: 0
        34      COPY                            1
        36      STORE_NAME                      8: a
        38      COPY                            1
        40      STORE_NAME                      9: b
        42      COPY                            1
        44      STORE_NAME                      10: c
        46      COPY                            1
        48      STORE_NAME                      11: d
        50      COPY                            1
        52      STORE_NAME                      12: e
        54      COPY                            1
        56      STORE_NAME                      13: f
        58      COPY                            1
        60      STORE_NAME                      14: g
        62      COPY                            1
        64      STORE_NAME                      15: h
        66      COPY                            1
        68      STORE_NAME                      16: i
        70      COPY                            1
        72      STORE_NAME                      17: j
        74      COPY                            1
        76      STORE_NAME                      18: k
        78      COPY                            1
        80      STORE_NAME                      19: l
        82      COPY                            1
        84      STORE_NAME                      20: m
        86      COPY                            1
        88      STORE_NAME                      21: n
        90      COPY                            1
        92      STORE_NAME                      22: o
        94      COPY                            1
        96      STORE_NAME                      23: p
        98      COPY                            1
        100     STORE_NAME                      24: q
        102     COPY                            1
        104     STORE_NAME                      25: r
        106     COPY                            1
        108     STORE_NAME                      26: s
        110     COPY                            1
        112     STORE_NAME                      27: t
        114     COPY                            1
        116     STORE_NAME                      28: u
        118     COPY                            1
        120     STORE_NAME                      29: v
        122     COPY                            1
        124     STORE_NAME                      30: w
        126     COPY                            1
        128     STORE_NAME                      31: x
        130     COPY                            1
        132     STORE_NAME                      32: y
        134     STORE_NAME                      33: z
        136     LOAD_NAME                       34: input
        138     PUSH_NULL                       
        140     LOAD_CONST                      4: 'Key > '
        142     CALL                            1
        150     LOAD_ATTR                       71: encode
        170     CALL                            0
        178     STORE_NAME                      36: key
        180     LOAD_NAME                       34: input
        182     PUSH_NULL                       
        184     LOAD_CONST                      5: 'IV  > '
        186     CALL                            1
        194     LOAD_ATTR                       71: encode
        214     CALL                            0
        222     STORE_NAME                      37: iv
        224     LOAD_NAME                       38: len
        226     PUSH_NULL                       
        228     LOAD_NAME                       36: key
        230     CALL                            1
        238     LOAD_CONST                      6: 32
        240     COMPARE_OP                      88 (==)
        244     POP_JUMP_IF_FALSE               111 (to 468)
        248     LOAD_NAME                       38: len
        250     PUSH_NULL                       
        252     LOAD_NAME                       37: iv
        254     CALL                            1
        262     LOAD_CONST                      7: 16
        264     COMPARE_OP                      88 (==)
        268     POP_JUMP_IF_FALSE               99 (to 468)
        272     LOAD_NAME                       4: unpad
        274     PUSH_NULL                       
        276     LOAD_NAME                       1: AES
        278     LOAD_ATTR                       78: new
        298     PUSH_NULL                       
        300     LOAD_NAME                       36: key
        302     LOAD_NAME                       1: AES
        304     LOAD_ATTR                       80: MODE_CBC
        324     LOAD_NAME                       37: iv
        326     CALL                            3
        334     LOAD_ATTR                       83: decrypt
        354     LOAD_CONST                      8: b'\x1fQer\xec\xb6\x05\xee\xc0g/\x82\x0c\xdb\xecZ\x13\xf8\x08\x01\tB:\xe4\xbdkb/r\xba\xf6\xc0\xe9\xe6M\xf7\xa1\x02&\x17p\x7f)\xb4\xe0\xdf\xe8w'
        356     CALL                            1
        364     LOAD_NAME                       1: AES
        366     LOAD_ATTR                       84: block_size
        386     CALL                            2
        394     STORE_NAME                      43: decrypted
        396     LOAD_CONST                      9: b'INTIGRITI'
        398     LOAD_NAME                       43: decrypted
        400     CONTAINS_OP                     0 (in)
        404     POP_JUMP_IF_FALSE               30 (to 466)
        408     LOAD_NAME                       6: print
        410     PUSH_NULL                       
        412     LOAD_CONST                      10: 'gg'
        414     CALL                            1
        422     POP_TOP                         
        424     LOAD_NAME                       6: print
        426     PUSH_NULL                       
        428     LOAD_NAME                       43: decrypted
        430     LOAD_ATTR                       89: decode
        450     CALL                            0
        458     CALL                            1
        466     POP_TOP                         
        468     DELETE_NAME                     43: decrypted
        470     DELETE_NAME                     36: key
        472     DELETE_NAME                     37: iv
        474     LOAD_CONST                      11: b'\xc0\xae\x13\x8a\xbb\x0b\xa1\x95\xf9\x8a\xe0\\\xb6\xc8\xd2\x1fHF*\x0bK\x11\xf2\x82\xfcIk\xd2|\xcdf\xd6@c\x17\xe9\xcc\xdd\x98O\xa5;=<\xea\\\x91\xf2\xc0I\x901)\x8bH\xab\xda}g\x95\x0f#<YN\x03\x94n\xd1\xed\xcf\x9a\xc4\xefU\x99\x92\xe7\xf0&^\xd9\xb9\xc7U\x7f\xce\x0eQ;9dU\xf2\x88\x17\xe2\xc0Q\x93&\xeb\x1f\xf9\'"$\x08?\x83~\xb1\xc8HK\x07\xce\xb2\x10\xd1\x9d\x99k\xba)X\xc5\x08\xec\xe7]\x81s\x9b\xdfsl\xad\xbc 8TM\xd9\xa1em;\xec\x03E\xa5EJ\xbaT:\'\xa3\xa9\xf4\xa9\x0b\xadL\xaer\xf1\x84\x02bI\xe3Ym-&\xb6\xae\\c\xa0\xbcJ@\xaf\xf9\x1d\x8bY\xa3\xa5\xe5b\xf3\xf1\x99b\xf2~\xbd\xf3\xd6\xf5m,\x82=u\x98G\x1b\x86s6\xcb\xf8x\xa9\x16\xfc\xe35\xd8\xca\x17K\xa4\xc6\x04d:\xbaN \xed\x15`\x8f\xd1\xe1\xfdHhr\xbc\xb08V\xb8\x8d\x83\x8a\xf2\x8e{\xe0M\xffs=\xfb\x8d;\xdf\xdd\xc1\x0fm\xeb{\xb5\x9bm\x83\xe7\xf9\x91F\xc0C\xdfP\rG\xd6\xfa\xd7Lb\x8eA\xe4\x008\xf2\xad\xd8\x0f\x9d\xb8\xbfM@\xf4\xca\xf4\xb2\xbbi\x0c\xff\x0fu\x9cT\x0b\xf8\x8e\x9c\x1e\xca\xbc\xcd\xaaG\xd9\x17xp\xd1B7\x0f\xe0\x914\xf1\xdb\xeczH\xbbc\xde\xfcyGA/\xce\x86\x91\xec\xe5:\xc1\x03\x8d]\x90J^\xdc\xa9+\x03Xh\xc3\xe9\x1cDxd\x1b\x0fF\x1f\x99\x18\x8e9DA{\x80\xea\xcf\xb0\xeb\xb0K\x8f\xe4\x07\x1f\x8e\x04n\xb8t\xe9\x13R\xf39\xf1\x17\x05\xfb\x00\xf8\xca\xfa}K\xa6\x8e+\xd5\xa9\x04\xb9I\xab+w\x93\xa8\xfek\xd3\x8bJt\xe3\xfea\xa1 \xb7\xb9\xae\x81\xe2:\xfc\x0b\x85\x15\xe4s\xef:xF\xd9\x83\xddi4\x9e6!\xc2\xbaP\\\xb4V6%\xc0"x\xd1\x15\xc1\x07\x10\xd0\xf9\x96\xee\xd6\xf1)\x9e\xe3\xb9\xe3T\xec\xdd\x8alF\x88\x101U\xed\xb8\xbcd\xfc\x02\xb3\xb4B\x04\xd4g\xc8\xc7\x83\x89^^\xc4\xfc\x02\xca\xcd\xb9\xa7\\|yU\xb71\xb4>\xa9\x1dxv4!\\\xe1\xc1\xe0?\xa3\xaf/(\x16\x0b\xcd\xd3\x99S\x0f\xe4\xfd\xa9\\\x17g\x9e\'N^\xca\x9f^\xec~G\xfa\xd9\xc5 R\xb1\x1f\x95\xaa\xe5:\xa7\x9f\xc2\x8bC\x88\xd2\xa1\xff\x83\x94a\x11J\xdb{\x1bb\x1aBs\x18\xef\xa7\xd7\x1e\xc3\xa4\xff\xa9v:M\xb2\xc59\x98\xe4f\x13!\xf5mz\xb1\x15\xdc\xf5x\xd3g\x0e%t\xda\x9aV\x0cQ\xe5Z{s5\xb1C\xe2!\xdf\xc4z\xaa9^/y\x01^\x99\xdb)4\x02,C\x16tQ\xa2Rj\x80f\xc5U\t\xbd\x1d\xaf/\xaf\x9b\x8cv\xd5\n\x0b\xf6$3\x97Ac\xd6\xff\xc0\x86\xe3\xe3\x1d\x87T\x1d\x8b\xab%S\x8a!\x9f\x1b\x9a$\xdb:\xf47\xa7,\x1cY\x9c*\xec\xcbt1\x9c\x9euGs\x18t\xf6\x81\xeb\xe0Dd\xedx\x02\xec"\xab\x80Bh\x03\xcb\x86\xe1*K\xa5O\xa3\xc2,q~\x87\x8a%\xcc%\x0c\xda-9F)\x00\x8b\xbe\x85\x17\xadl\xd2\xb0\x8c\x8e;U*\xfc4\xd6\r>\x04\xbe\x7f\x88\xc7T\xbd0\xa6\xe85\xa9.\x19\x8d\xfa%\x85\n\xe2\x84\xa8&\xcd\'\xb9\xd6\xebK\x8d\x10}\xc2\xd1\xde@9Uf\xa4_\xa2\xb9X\xd6;\xf9I\xcfc\xfc6\x94\xa5\x834\xbeBD\xfa\xfd\xb8.\x82\xfb)a\xf6L\x95V#\x05\xea}6\xe0C\xf7\xf4\xd3\xed\xba\x02v\xe5 \xcch,{\xad\xc7\xfc\xe1\xaf\xb3\x14R\xdb1\x07JK:g8\x8b\x9bw\x17\x1d\x13\x8ff\x8a\x0e\x98\xcd\xc4\xb1e^\x8c\xbai\x05\xa2\x9e\xc9\xd8{ D\x9c\x0f\xc1\x8a\x0b\x92\'\xed \x8f,\x00o\xa3\xb8%X\xa3\xde\xec\xfdu\x1a\xc9\xac\xfd\x1f\xf9<|\xd4G\x1a.\xac^\xfc\xc9I\x1fkG\xe9\xa1\x0e\xd2\x1b\x90\xb7\xfd\xd0.{\x00d6Y\x06\xcb,L\x9a\x82\xb5\xe6\x8f\xedp=\xbf\xbdFP\x88\xdf!\x0f}]\xecK\x0b3\x97f\xf6\'\x90\xe7\x9ex:xE\x9c\xe0\xbe\x14\xc8\x0f\xa3\xc8\xdag1\xe5{\xe1i|=\x14\x81wy\xb8W\xe7?j\x95;p\x1a\x95\xc7#6\xc3\x00\xec8\xae;\xc9\xf7\xcc\x0f\xb4K\x17w\x1f\xc9]\xa8D&\xb1\xacrs\xbeI\xc7\xab\xf29s\x85\xd7\xaf0\xb0|\x13\xa6\x96\x8f\xe2\x97\x84\x8ag\xf3\xb9ow!b\xa8\xd1\x83a[*$\x8a\xfdp\xc2\x7f\xb1f\xd4\x90z\xe3V\x16\xd8\xed\xa2@\n_\xb4\xd2)\xd4\x14\x85\xbay\xf65#3\xbf\x14\xbf\x1a\xb4\xcb\xd9\xc7\x0f\xe8\xa5!\xa0\xae\x00\x9a\xdb\xd8\xfbg\x8f\x99\xca&\x9f\xe7\x0c\xf3\x03\xd3rw\xe2P\x8c\x01\x0b\xa14-U\xb3\x8b?\x94\xfd\xed#\x99w4\xa2\xf7\xfaS\x10\xa5F\xcbY\x1a\xe7\x87I\xed\x02t,|\xb6c\x8f\xa4)\xa7\x8e\xe2\x18<\xaf\x05z g\xda\xa3\x19\xefq\xe4?\x92\xfdj+y}|\xc6\r}\xad\xd8\xecp\x96v\x8ah\x8b_\xec?\xfbpg\xc5\xfe\x9d=\x063\x17\x96\xe2>\xb1\xed-l\x95b\xb6\x81\xebF-\x1b\x12\xc2\x0b\xdeG\xbd\xdc\xe3\xf56u\xfd\x14\x17V\x8c\x87\x17_m?\xf7\xc3\xc2\xf0\x80;\x03\xea\xc9\xfd\x93~\xeff\x9b\xc5\r\x92\x9atb\xf9\x16\x8c&m4\xb5/F@\x12\')\xea\xff\x97\xf5C;\xd7\x08\xa0\xac`\xc5#\x8b\x80\t\xe4\xf1\x99\x81\xc9\xa7g\xe0\xb1\x02)CZVz\xa6\xcb\x84@!\x98\xf9n \xa0e.3\xa3I\xe8\xcd\x8a\x9d\xb6\xdf\x18G\xdd\xf8T6&\xaa\xde\xb6\x9d\xfb\xdb\x17\x00H\xe3Lm|\xc8\x80\xb0\x03\xd1\xd2\xaaw~\xa0\x00P\x1f\x1a_\x8b\t\x81\xc8p\xfa.\xfb\xd8;\x13\xbb\x80$\xe3\xa4\x05*\x91\x9eD$cc\xaf@\x9b\xaa\xb7&\xaf\x1a\xa1L/X\xc8\xafW\xa3\xb6\xd1\r\xa4\xe8\x91 ^4\xd4\xc7V7\xc6\xe4\x11\x12\xe0{x\x85\xbb\x92\x07\xc0\xd3\xec\xf2JcX\xdb\xcd\xda\xae\x80\xfa\x92\xae\xae&\x07\xaf\x86\xf8i\xabai\xed\x0c`'
        476     STORE_NAME                      45: i_wonder_what_this_decrypts_to
        478     LOAD_NAME                       4: unpad
        480     PUSH_NULL                       
        482     LOAD_NAME                       1: AES
        484     LOAD_ATTR                       78: new
        504     PUSH_NULL                       
        506     LOAD_CONST                      12: b'/\xa0\xaa<?\xb54q\xdb\x00\x8e\xfe w\xae\x89\xf3R3\xd7.\x83c\xe6\xb6E\xac|\xfd\x92\x95j'
        508     LOAD_NAME                       1: AES
        510     LOAD_ATTR                       80: MODE_CBC
        530     LOAD_CONST                      13: b'\x1fdu\xae\x8f\x9a\xa5\x8b,\x94\xa0T\xe5ib\xd0'
        532     CALL                            3
        540     LOAD_ATTR                       83: decrypt
        560     LOAD_NAME                       45: i_wonder_what_this_decrypts_to
        562     CALL                            1
        570     LOAD_NAME                       1: AES
        572     LOAD_ATTR                       84: block_size
        592     CALL                            2
        600     POP_TOP                         
        602     LOAD_NAME                       9: b
        604     POP_TOP                         
        606     LOAD_NAME                       25: r
        608     POP_TOP                         
        610     LOAD_NAME                       32: y
        612     POP_TOP                         
        614     LOAD_NAME                       9: b
        616     POP_TOP                         
        618     LOAD_NAME                       12: e
        620     POP_TOP                         
        622     LOAD_NAME                       13: f
        624     POP_TOP                         
        626     LOAD_NAME                       12: e
        628     POP_TOP                         
        630     LOAD_NAME                       17: j
        632     POP_TOP                         
        634     LOAD_NAME                       21: n
        636     POP_TOP                         
        638     LOAD_NAME                       18: k
        640     POP_TOP                         
        642     LOAD_NAME                       16: i
        644     POP_TOP                         
        646     LOAD_NAME                       11: d
        648     POP_TOP                         
        650     LOAD_NAME                       22: o
        652     POP_TOP                         
        654     LOAD_NAME                       26: s
        656     POP_TOP                         
        658     LOAD_NAME                       9: b
        660     POP_TOP                         
        662     LOAD_NAME                       22: o
        664     POP_TOP                         
        666     LOAD_NAME                       14: g
        668     POP_TOP                         
        670     LOAD_NAME                       28: u
        672     POP_TOP                         
        674     LOAD_NAME                       16: i
        676     POP_TOP                         
        678     LOAD_NAME                       15: h
        680     POP_TOP                         
        682     LOAD_NAME                       8: a
        684     POP_TOP                         
        686     LOAD_NAME                       14: g
        688     POP_TOP                         
        690     LOAD_NAME                       26: s
        692     POP_TOP                         
        694     LOAD_NAME                       12: e
        696     POP_TOP                         
        698     LOAD_NAME                       23: p
        700     POP_TOP                         
        702     LOAD_NAME                       31: x
        704     POP_TOP                         
        706     LOAD_NAME                       12: e
        708     POP_TOP                         
        710     LOAD_NAME                       32: y
        712     POP_TOP                         
        714     LOAD_NAME                       30: w
        716     POP_TOP                         
        718     LOAD_NAME                       28: u
        720     POP_TOP                         
        722     LOAD_NAME                       13: f
        724     POP_TOP                         
        726     LOAD_NAME                       16: i
        728     POP_TOP                         
        730     LOAD_NAME                       8: a
        732     POP_TOP                         
        734     LOAD_NAME                       33: z
        736     POP_TOP                         
        738     LOAD_NAME                       31: x
        740     POP_TOP                         
        742     LOAD_NAME                       22: o
        744     POP_TOP                         
        746     LOAD_NAME                       31: x
        748     POP_TOP                         
        750     LOAD_NAME                       33: z
        752     POP_TOP                         
        754     LOAD_NAME                       9: b
        756     POP_TOP                         
        758     LOAD_NAME                       20: m
        760     POP_TOP                         
        762     LOAD_NAME                       27: t
        764     POP_TOP                         
        766     LOAD_NAME                       17: j
        768     POP_TOP                         
        770     LOAD_NAME                       25: r
        772     POP_TOP                         
        774     LOAD_NAME                       10: c
        776     POP_TOP                         
        778     LOAD_NAME                       13: f
        780     POP_TOP                         
        782     LOAD_NAME                       26: s
        784     POP_TOP                         
        786     LOAD_NAME                       18: k
        788     POP_TOP                         
        790     LOAD_NAME                       21: n
        792     POP_TOP                         
        794     LOAD_NAME                       23: p
        796     POP_TOP                         
        798     LOAD_NAME                       18: k
        800     POP_TOP                         
        802     LOAD_NAME                       19: l
        804     POP_TOP                         
        806     LOAD_NAME                       11: d
        808     POP_TOP                         
        810     LOAD_NAME                       15: h
        812     POP_TOP                         
        814     LOAD_NAME                       33: z
        816     POP_TOP                         
        818     LOAD_NAME                       17: j
        820     POP_TOP                         
        822     LOAD_NAME                       8: a
        824     POP_TOP                         
        826     LOAD_NAME                       28: u
        828     POP_TOP                         
        830     LOAD_NAME                       31: x
        832     POP_TOP                         
        834     LOAD_NAME                       8: a
        836     POP_TOP                         
        838     LOAD_NAME                       32: y
        840     POP_TOP                         
        842     LOAD_NAME                       22: o
        844     POP_TOP                         
        846     LOAD_NAME                       9: b
        848     POP_TOP                         
        850     LOAD_NAME                       16: i
        852     POP_TOP                         
        854     LOAD_NAME                       11: d
        856     POP_TOP                         
        858     LOAD_NAME                       29: v
        860     POP_TOP                         
        862     LOAD_NAME                       15: h
        864     POP_TOP                         
        866     LOAD_NAME                       21: n
        868     POP_TOP                         
        870     LOAD_NAME                       8: a
        872     POP_TOP                         
        874     LOAD_NAME                       24: q
        876     POP_TOP                         
        878     LOAD_NAME                       14: g
        880     POP_TOP                         
        882     LOAD_NAME                       9: b
        884     POP_TOP                         
        886     LOAD_NAME                       31: x
        888     POP_TOP                         
        890     LOAD_NAME                       33: z
        892     POP_TOP                         
        894     LOAD_NAME                       13: f
        896     POP_TOP                         
        898     LOAD_NAME                       26: s
        900     POP_TOP                         
        902     LOAD_NAME                       17: j
        904     POP_TOP                         
        906     LOAD_NAME                       32: y
        908     POP_TOP                         
        910     LOAD_NAME                       25: r
        912     POP_TOP                         
        914     LOAD_NAME                       30: w
        916     POP_TOP                         
        918     LOAD_NAME                       8: a
        920     POP_TOP                         
        922     LOAD_NAME                       8: a
        924     POP_TOP                         
        926     LOAD_NAME                       21: n
        928     POP_TOP                         
        930     LOAD_NAME                       21: n
        932     POP_TOP                         
        934     LOAD_NAME                       11: d
        936     POP_TOP                         
        938     LOAD_NAME                       13: f
        940     POP_TOP                         
        942     LOAD_NAME                       22: o
        944     POP_TOP                         
        946     LOAD_NAME                       20: m
        948     POP_TOP                         
        950     LOAD_NAME                       23: p
        952     POP_TOP                         
        954     LOAD_NAME                       27: t
        956     POP_TOP                         
        958     LOAD_NAME                       15: h
        960     POP_TOP                         
        962     LOAD_NAME                       29: v
        964     POP_TOP                         
        966     LOAD_NAME                       26: s
        968     POP_TOP                         
        970     LOAD_NAME                       9: b
        972     POP_TOP                         
        974     LOAD_NAME                       24: q
        976     POP_TOP                         
        978     LOAD_NAME                       18: k
        980     POP_TOP                         
        982     LOAD_NAME                       14: g
        984     POP_TOP                         
        986     LOAD_NAME                       31: x
        988     POP_TOP                         
        990     LOAD_NAME                       20: m
        992     POP_TOP                         
        994     LOAD_NAME                       24: q
        996     POP_TOP                         
        998     LOAD_NAME                       12: e
        1000    POP_TOP                         
        1002    LOAD_NAME                       19: l
        1004    POP_TOP                         
        1006    LOAD_NAME                       24: q
        1008    POP_TOP                         
        1010    LOAD_NAME                       8: a
        1012    POP_TOP                         
        1014    LOAD_NAME                       16: i
        1016    POP_TOP                         
        1018    LOAD_NAME                       13: f
        1020    POP_TOP                         
        1022    LOAD_NAME                       25: r
        1024    POP_TOP                         
        1026    LOAD_NAME                       13: f
        1028    POP_TOP                         
        1030    LOAD_NAME                       18: k
        1032    POP_TOP                         
        1034    LOAD_NAME                       13: f
        1036    POP_TOP                         
        1038    LOAD_NAME                       20: m
        1040    POP_TOP                         
        1042    LOAD_NAME                       22: o
        1044    POP_TOP                         
        1046    LOAD_NAME                       21: n
        1048    POP_TOP                         
        1050    LOAD_NAME                       33: z
        1052    POP_TOP                         
        1054    LOAD_NAME                       29: v
        1056    POP_TOP                         
        1058    LOAD_NAME                       21: n
        1060    POP_TOP                         
        1062    LOAD_NAME                       18: k
        1064    POP_TOP                         
        1066    LOAD_NAME                       20: m
        1068    POP_TOP                         
        1070    LOAD_NAME                       25: r
        1072    POP_TOP                         
        1074    LOAD_NAME                       14: g
        1076    POP_TOP                         
        1078    LOAD_NAME                       20: m
        1080    POP_TOP                         
        1082    LOAD_NAME                       15: h
        1084    POP_TOP                         
        1086    LOAD_NAME                       10: c
        1088    POP_TOP                         
        1090    LOAD_NAME                       10: c
        1092    POP_TOP                         
        1094    LOAD_NAME                       28: u
        1096    POP_TOP                         
        1098    LOAD_NAME                       21: n
        1100    POP_TOP                         
        1102    LOAD_NAME                       22: o
        1104    POP_TOP                         
        1106    LOAD_NAME                       16: i
        1108    POP_TOP                         
        1110    LOAD_NAME                       25: r
        1112    POP_TOP                         
        1114    LOAD_NAME                       31: x
        1116    POP_TOP                         
        1118    LOAD_NAME                       31: x
        1120    POP_TOP                         
        1122    LOAD_NAME                       31: x
        1124    POP_TOP                         
        1126    LOAD_NAME                       9: b
        1128    POP_TOP                         
        1130    LOAD_NAME                       15: h
        1132    POP_TOP                         
        1134    LOAD_NAME                       8: a
        1136    POP_TOP                         
        1138    LOAD_NAME                       13: f
        1140    POP_TOP                         
        1142    LOAD_NAME                       20: m
        1144    POP_TOP                         
        1146    LOAD_NAME                       25: r
        1148    POP_TOP                         
        1150    LOAD_NAME                       26: s
        1152    POP_TOP                         
        1154    LOAD_NAME                       9: b
        1156    POP_TOP                         
        1158    LOAD_NAME                       28: u
        1160    POP_TOP                         
        1162    LOAD_NAME                       26: s
        1164    POP_TOP                         
        1166    LOAD_NAME                       12: e
        1168    POP_TOP                         
        1170    LOAD_NAME                       16: i
        1172    POP_TOP                         
        1174    LOAD_NAME                       30: w
        1176    POP_TOP                         
        1178    LOAD_NAME                       21: n
        1180    POP_TOP                         
        1182    LOAD_NAME                       30: w
        1184    POP_TOP                         
        1186    LOAD_NAME                       16: i
        1188    POP_TOP                         
        1190    LOAD_NAME                       32: y
        1192    POP_TOP                         
        1194    LOAD_NAME                       16: i
        1196    POP_TOP                         
        1198    LOAD_NAME                       9: b
        1200    POP_TOP                         
        1202    LOAD_NAME                       9: b
        1204    POP_TOP                         
        1206    LOAD_NAME                       23: p
        1208    POP_TOP                         
        1210    LOAD_NAME                       25: r
        1212    POP_TOP                         
        1214    LOAD_NAME                       29: v
        1216    POP_TOP                         
        1218    LOAD_NAME                       16: i
        1220    POP_TOP                         
        1222    LOAD_NAME                       12: e
        1224    POP_TOP                         
        1226    LOAD_NAME                       21: n
        1228    POP_TOP                         
        1230    LOAD_NAME                       31: x
        1232    POP_TOP                         
        1234    LOAD_NAME                       28: u
        1236    POP_TOP                         
        1238    LOAD_NAME                       24: q
        1240    POP_TOP                         
        1242    LOAD_NAME                       25: r
        1244    POP_TOP                         
        1246    LOAD_NAME                       22: o
        1248    POP_TOP                         
        1250    LOAD_NAME                       20: m
        1252    POP_TOP                         
        1254    LOAD_NAME                       11: d
        1256    POP_TOP                         
        1258    LOAD_NAME                       30: w
        1260    POP_TOP                         
        1262    LOAD_NAME                       22: o
        1264    POP_TOP                         
        1266    LOAD_NAME                       13: f
        1268    POP_TOP                         
        1270    LOAD_NAME                       10: c
        1272    POP_TOP                         
        1274    LOAD_NAME                       28: u
        1276    POP_TOP                         
        1278    LOAD_NAME                       23: p
        1280    POP_TOP                         
        1282    LOAD_NAME                       29: v
        1284    POP_TOP                         
        1286    LOAD_NAME                       28: u
        1288    POP_TOP                         
        1290    LOAD_NAME                       23: p
        1292    POP_TOP                         
        1294    LOAD_NAME                       11: d
        1296    POP_TOP                         
        1298    LOAD_NAME                       12: e
        1300    POP_TOP                         
        1302    LOAD_NAME                       30: w
        1304    POP_TOP                         
        1306    LOAD_NAME                       22: o
        1308    POP_TOP                         
        1310    LOAD_NAME                       32: y
        1312    POP_TOP                         
        1314    LOAD_NAME                       17: j
        1316    POP_TOP                         
        1318    LOAD_NAME                       17: j
        1320    POP_TOP                         
        1322    LOAD_NAME                       23: p
        1324    POP_TOP                         
        1326    LOAD_NAME                       27: t
        1328    POP_TOP                         
        1330    LOAD_NAME                       17: j
        1332    POP_TOP                         
        1334    LOAD_NAME                       16: i
        1336    POP_TOP                         
        1338    LOAD_NAME                       19: l
        1340    POP_TOP                         
        1342    LOAD_NAME                       12: e
        1344    POP_TOP                         
        1346    LOAD_NAME                       20: m
        1348    POP_TOP                         
        1350    LOAD_NAME                       27: t
        1352    POP_TOP                         
        1354    LOAD_NAME                       20: m
        1356    POP_TOP                         
        1358    LOAD_NAME                       29: v
        1360    POP_TOP                         
        1362    LOAD_NAME                       22: o
        1364    POP_TOP                         
        1366    LOAD_NAME                       30: w
        1368    POP_TOP                         
        1370    LOAD_NAME                       8: a
        1372    POP_TOP                         
        1374    LOAD_NAME                       10: c
        1376    POP_TOP                         
        1378    LOAD_NAME                       12: e
        1380    POP_TOP                         
        1382    LOAD_NAME                       21: n
        1384    POP_TOP                         
        1386    LOAD_NAME                       21: n
        1388    POP_TOP                         
        1390    LOAD_NAME                       22: o
        1392    POP_TOP                         
        1394    LOAD_NAME                       8: a
        1396    POP_TOP                         
        1398    LOAD_NAME                       32: y
        1400    POP_TOP                         
        1402    LOAD_NAME                       18: k
        1404    POP_TOP                         
        1406    LOAD_NAME                       11: d
        1408    POP_TOP                         
        1410    LOAD_NAME                       33: z
        1412    POP_TOP                         
        1414    LOAD_NAME                       22: o
        1416    POP_TOP                         
        1418    LOAD_NAME                       17: j
        1420    POP_TOP                         
        1422    LOAD_NAME                       12: e
        1424    POP_TOP                         
        1426    LOAD_NAME                       24: q
        1428    POP_TOP                         
        1430    LOAD_NAME                       12: e
        1432    POP_TOP                         
        1434    LOAD_NAME                       29: v
        1436    POP_TOP                         
        1438    LOAD_NAME                       16: i
        1440    POP_TOP                         
        1442    LOAD_NAME                       20: m
        1444    POP_TOP                         
        1446    LOAD_NAME                       9: b
        1448    POP_TOP                         
        1450    LOAD_NAME                       9: b
        1452    POP_TOP                         
        1454    LOAD_NAME                       13: f
        1456    POP_TOP                         
        1458    LOAD_NAME                       20: m
        1460    POP_TOP                         
        1462    LOAD_NAME                       32: y
        1464    POP_TOP                         
        1466    LOAD_NAME                       10: c
        1468    POP_TOP                         
        1470    LOAD_NAME                       20: m
        1472    POP_TOP                         
        1474    LOAD_NAME                       20: m
        1476    POP_TOP                         
        1478    LOAD_NAME                       14: g
        1480    POP_TOP                         
        1482    LOAD_NAME                       29: v
        1484    POP_TOP                         
        1486    LOAD_NAME                       9: b
        1488    POP_TOP                         
        1490    LOAD_NAME                       13: f
        1492    POP_TOP                         
        1494    LOAD_NAME                       33: z
        1496    POP_TOP                         
        1498    LOAD_NAME                       21: n
        1500    POP_TOP                         
        1502    LOAD_NAME                       10: c
        1504    POP_TOP                         
        1506    LOAD_NAME                       8: a
        1508    POP_TOP                         
        1510    LOAD_NAME                       29: v
        1512    POP_TOP                         
        1514    LOAD_NAME                       23: p
        1516    POP_TOP                         
        1518    LOAD_NAME                       18: k
        1520    POP_TOP                         
        1522    LOAD_NAME                       26: s
        1524    POP_TOP                         
        1526    LOAD_NAME                       11: d
        1528    POP_TOP                         
        1530    LOAD_NAME                       23: p
        1532    POP_TOP                         
        1534    LOAD_NAME                       26: s
        1536    POP_TOP                         
        1538    LOAD_NAME                       9: b
        1540    POP_TOP                         
        1542    LOAD_NAME                       17: j
        1544    POP_TOP                         
        1546    LOAD_NAME                       20: m
        1548    POP_TOP                         
        1550    LOAD_NAME                       14: g
        1552    POP_TOP                         
        1554    LOAD_NAME                       12: e
        1556    POP_TOP                         
        1558    LOAD_NAME                       18: k
        1560    POP_TOP                         
        1562    LOAD_NAME                       32: y
        1564    POP_TOP                         
        1566    LOAD_NAME                       32: y
        1568    POP_TOP                         
        1570    LOAD_NAME                       25: r
        1572    POP_TOP                         
        1574    LOAD_NAME                       11: d
        1576    POP_TOP                         
        1578    LOAD_NAME                       33: z
        1580    POP_TOP                         
        1582    LOAD_NAME                       31: x
        1584    POP_TOP                         
        1586    LOAD_NAME                       23: p
        1588    POP_TOP                         
        1590    LOAD_NAME                       23: p
        1592    POP_TOP                         
        1594    LOAD_NAME                       28: u
        1596    POP_TOP                         
        1598    LOAD_NAME                       25: r
        1600    POP_TOP                         
        1602    LOAD_NAME                       30: w
        1604    POP_TOP                         
        1606    LOAD_NAME                       10: c
        1608    POP_TOP                         
        1610    LOAD_NAME                       22: o
        1612    POP_TOP                         
        1614    LOAD_NAME                       20: m
        1616    POP_TOP                         
        1618    LOAD_NAME                       13: f
        1620    POP_TOP                         
        1622    LOAD_NAME                       17: j
        1624    POP_TOP                         
        1626    LOAD_NAME                       29: v
        1628    POP_TOP                         
        1630    LOAD_NAME                       21: n
        1632    POP_TOP                         
        1634    LOAD_NAME                       22: o
        1636    POP_TOP                         
        1638    LOAD_NAME                       22: o
        1640    POP_TOP                         
        1642    LOAD_NAME                       28: u
        1644    POP_TOP                         
        1646    LOAD_NAME                       29: v
        1648    POP_TOP                         
        1650    LOAD_NAME                       16: i
        1652    POP_TOP                         
        1654    LOAD_NAME                       20: m
        1656    POP_TOP                         
        1658    LOAD_NAME                       31: x
        1660    POP_TOP                         
        1662    LOAD_NAME                       17: j
        1664    POP_TOP                         
        1666    LOAD_NAME                       9: b
        1668    POP_TOP                         
        1670    LOAD_NAME                       10: c
        1672    POP_TOP                         
        1674    LOAD_NAME                       11: d
        1676    POP_TOP                         
        1678    LOAD_NAME                       9: b
        1680    POP_TOP                         
        1682    LOAD_NAME                       30: w
        1684    POP_TOP                         
        1686    LOAD_NAME                       28: u
        1688    POP_TOP                         
        1690    LOAD_NAME                       22: o
        1692    POP_TOP                         
        1694    LOAD_NAME                       22: o
        1696    POP_TOP                         
        1698    LOAD_NAME                       31: x
        1700    POP_TOP                         
        1702    LOAD_NAME                       15: h
        1704    POP_TOP                         
        1706    LOAD_NAME                       14: g
        1708    POP_TOP                         
        1710    LOAD_NAME                       10: c
        1712    POP_TOP                         
        1714    LOAD_NAME                       17: j
        1716    POP_TOP                         
        1718    LOAD_NAME                       12: e
        1720    POP_TOP                         
        1722    LOAD_NAME                       28: u
        1724    POP_TOP                         
        1726    LOAD_NAME                       16: i
        1728    POP_TOP                         
        1730    LOAD_NAME                       29: v
        1732    POP_TOP                         
        1734    LOAD_NAME                       13: f
        1736    POP_TOP                         
        1738    LOAD_NAME                       32: y
        1740    POP_TOP                         
        1742    LOAD_NAME                       11: d
        1744    POP_TOP                         
        1746    LOAD_NAME                       19: l
        1748    POP_TOP                         
        1750    LOAD_NAME                       13: f
        1752    POP_TOP                         
        1754    LOAD_NAME                       28: u
        1756    POP_TOP                         
        1758    LOAD_NAME                       10: c
        1760    POP_TOP                         
        1762    LOAD_NAME                       8: a
        1764    POP_TOP                         
        1766    LOAD_NAME                       17: j
        1768    POP_TOP                         
        1770    LOAD_NAME                       32: y
        1772    POP_TOP                         
        1774    LOAD_NAME                       16: i
        1776    POP_TOP                         
        1778    LOAD_NAME                       9: b
        1780    POP_TOP                         
        1782    LOAD_NAME                       15: h
        1784    POP_TOP                         
        1786    LOAD_NAME                       19: l
        1788    POP_TOP                         
        1790    LOAD_NAME                       29: v
        1792    POP_TOP                         
        1794    LOAD_NAME                       10: c
        1796    POP_TOP                         
        1798    LOAD_NAME                       26: s
        1800    POP_TOP                         
        1802    LOAD_NAME                       16: i
        1804    POP_TOP                         
        1806    LOAD_NAME                       17: j
        1808    POP_TOP                         
        1810    LOAD_NAME                       30: w
        1812    POP_TOP                         
        1814    LOAD_NAME                       12: e
        1816    POP_TOP                         
        1818    LOAD_NAME                       27: t
        1820    POP_TOP                         
        1822    LOAD_NAME                       15: h
        1824    POP_TOP                         
        1826    LOAD_NAME                       26: s
        1828    POP_TOP                         
        1830    LOAD_NAME                       15: h
        1832    POP_TOP                         
        1834    LOAD_NAME                       21: n
        1836    POP_TOP                         
        1838    LOAD_NAME                       30: w
        1840    POP_TOP                         
        1842    LOAD_NAME                       9: b
        1844    POP_TOP                         
        1846    LOAD_NAME                       20: m
        1848    POP_TOP                         
        1850    LOAD_NAME                       29: v
        1852    POP_TOP                         
        1854    LOAD_NAME                       18: k
        1856    POP_TOP                         
        1858    LOAD_NAME                       13: f
        1860    POP_TOP                         
        1862    LOAD_NAME                       27: t
        1864    POP_TOP                         
        1866    LOAD_NAME                       29: v
        1868    POP_TOP                         
        1870    LOAD_NAME                       30: w
        1872    POP_TOP                         
        1874    LOAD_NAME                       22: o
        1876    POP_TOP                         
        1878    LOAD_NAME                       22: o
        1880    POP_TOP                         
        1882    LOAD_NAME                       26: s
        1884    POP_TOP                         
        1886    LOAD_NAME                       12: e
        1888    POP_TOP                         
        1890    LOAD_NAME                       31: x
        1892    POP_TOP                         
        1894    LOAD_NAME                       14: g
        1896    POP_TOP                         
        1898    LOAD_NAME                       25: r
        1900    POP_TOP                         
        1902    LOAD_NAME                       11: d
        1904    POP_TOP                         
        1906    LOAD_NAME                       14: g
        1908    POP_TOP                         
        1910    LOAD_NAME                       29: v
        1912    POP_TOP                         
        1914    LOAD_NAME                       16: i
        1916    POP_TOP                         
        1918    LOAD_NAME                       23: p
        1920    POP_TOP                         
        1922    LOAD_NAME                       14: g
        1924    POP_TOP                         
        1926    LOAD_NAME                       10: c
        1928    POP_TOP                         
        1930    LOAD_NAME                       32: y
        1932    POP_TOP                         
        1934    LOAD_NAME                       19: l
        1936    POP_TOP                         
        1938    LOAD_NAME                       16: i
        1940    POP_TOP                         
        1942    LOAD_NAME                       32: y
        1944    POP_TOP                         
        1946    LOAD_NAME                       25: r
        1948    POP_TOP                         
        1950    LOAD_NAME                       26: s
        1952    POP_TOP                         
        1954    LOAD_NAME                       30: w
        1956    POP_TOP                         
        1958    LOAD_NAME                       13: f
        1960    POP_TOP                         
        1962    LOAD_NAME                       23: p
        1964    POP_TOP                         
        1966    LOAD_NAME                       29: v
        1968    POP_TOP                         
        1970    LOAD_NAME                       9: b
        1972    POP_TOP                         
        1974    LOAD_NAME                       25: r
        1976    POP_TOP                         
        1978    LOAD_NAME                       15: h
        1980    POP_TOP                         
        1982    LOAD_NAME                       20: m
        1984    POP_TOP                         
        1986    LOAD_NAME                       25: r
        1988    POP_TOP                         
        1990    LOAD_NAME                       14: g
        1992    POP_TOP                         
        1994    LOAD_NAME                       27: t
        1996    POP_TOP                         
        1998    LOAD_NAME                       33: z
        2000    POP_TOP                         
        2002    LOAD_NAME                       12: e
        2004    POP_TOP                         
        2006    LOAD_NAME                       29: v
        2008    POP_TOP                         
        2010    LOAD_NAME                       23: p
        2012    POP_TOP                         
        2014    LOAD_NAME                       11: d
        2016    POP_TOP                         
        2018    LOAD_NAME                       9: b
        2020    POP_TOP                         
        2022    LOAD_NAME                       28: u
        2024    POP_TOP                         
        2026    LOAD_NAME                       14: g
        2028    POP_TOP                         
        2030    LOAD_NAME                       14: g
        2032    POP_TOP                         
        2034    LOAD_NAME                       13: f
        2036    POP_TOP                         
        2038    LOAD_NAME                       29: v
        2040    POP_TOP                         
        2042    LOAD_NAME                       29: v
        2044    POP_TOP                         
        2046    LOAD_NAME                       19: l
        2048    POP_TOP                         
        2050    LOAD_NAME                       9: b
        2052    POP_TOP                         
        2054    LOAD_NAME                       16: i
        2056    POP_TOP                         
        2058    LOAD_NAME                       15: h
        2060    POP_TOP                         
        2062    LOAD_NAME                       30: w
        2064    POP_TOP                         
        2066    LOAD_NAME                       9: b
        2068    POP_TOP                         
        2070    LOAD_NAME                       25: r
        2072    POP_TOP                         
        2074    LOAD_NAME                       23: p
        2076    POP_TOP                         
        2078    LOAD_NAME                       12: e
        2080    POP_TOP                         
        2082    LOAD_NAME                       20: m
        2084    POP_TOP                         
        2086    LOAD_NAME                       33: z
        2088    POP_TOP                         
        2090    LOAD_NAME                       20: m
        2092    POP_TOP                         
        2094    LOAD_NAME                       9: b
        2096    POP_TOP                         
        2098    LOAD_NAME                       19: l
        2100    POP_TOP                         
        2102    LOAD_NAME                       25: r
        2104    POP_TOP                         
        2106    LOAD_NAME                       33: z
        2108    POP_TOP                         
        2110    LOAD_NAME                       8: a
        2112    POP_TOP                         
        2114    LOAD_NAME                       26: s
        2116    POP_TOP                         
        2118    LOAD_NAME                       9: b
        2120    POP_TOP                         
        2122    LOAD_NAME                       26: s
        2124    POP_TOP                         
        2126    LOAD_NAME                       28: u
        2128    POP_TOP                         
        2130    LOAD_NAME                       12: e
        2132    POP_TOP                         
        2134    LOAD_NAME                       10: c
        2136    POP_TOP                         
        2138    LOAD_NAME                       14: g
        2140    POP_TOP                         
        2142    LOAD_NAME                       14: g
        2144    POP_TOP                         
        2146    LOAD_NAME                       22: o
        2148    POP_TOP                         
        2150    LOAD_NAME                       13: f
        2152    POP_TOP                         
        2154    LOAD_NAME                       31: x
        2156    POP_TOP                         
        2158    LOAD_NAME                       12: e
        2160    POP_TOP                         
        2162    LOAD_NAME                       15: h
        2164    POP_TOP                         
        2166    LOAD_NAME                       30: w
        2168    POP_TOP                         
        2170    LOAD_NAME                       12: e
        2172    POP_TOP                         
        2174    LOAD_NAME                       31: x
        2176    POP_TOP                         
        2178    LOAD_NAME                       11: d
        2180    POP_TOP                         
        2182    LOAD_NAME                       24: q
        2184    POP_TOP                         
        2186    LOAD_NAME                       22: o
        2188    POP_TOP                         
        2190    LOAD_NAME                       30: w
        2192    POP_TOP                         
        2194    LOAD_NAME                       24: q
        2196    POP_TOP                         
        2198    LOAD_NAME                       30: w
        2200    POP_TOP                         
        2202    LOAD_NAME                       23: p
        2204    POP_TOP                         
        2206    LOAD_NAME                       9: b
        2208    POP_TOP                         
        2210    LOAD_NAME                       30: w
        2212    POP_TOP                         
        2214    LOAD_NAME                       19: l
        2216    POP_TOP                         
        2218    LOAD_NAME                       30: w
        2220    POP_TOP                         
        2222    LOAD_NAME                       24: q
        2224    POP_TOP                         
        2226    LOAD_NAME                       25: r
        2228    POP_TOP                         
        2230    LOAD_NAME                       19: l
        2232    POP_TOP                         
        2234    LOAD_NAME                       32: y
        2236    POP_TOP                         
        2238    LOAD_NAME                       21: n
        2240    POP_TOP                         
        2242    LOAD_NAME                       28: u
        2244    POP_TOP                         
        2246    LOAD_NAME                       23: p
        2248    POP_TOP                         
        2250    LOAD_NAME                       14: g
        2252    POP_TOP                         
        2254    LOAD_NAME                       22: o
        2256    POP_TOP                         
        2258    LOAD_NAME                       13: f
        2260    POP_TOP                         
        2262    LOAD_NAME                       32: y
        2264    POP_TOP                         
        2266    LOAD_NAME                       21: n
        2268    POP_TOP                         
        2270    LOAD_NAME                       14: g
        2272    POP_TOP                         
        2274    LOAD_NAME                       25: r
        2276    POP_TOP                         
        2278    LOAD_NAME                       9: b
        2280    POP_TOP                         
        2282    LOAD_NAME                       18: k
        2284    POP_TOP                         
        2286    LOAD_NAME                       8: a
        2288    POP_TOP                         
        2290    LOAD_NAME                       19: l
        2292    POP_TOP                         
        2294    LOAD_NAME                       11: d
        2296    POP_TOP                         
        2298    LOAD_NAME                       17: j
        2300    POP_TOP                         
        2302    LOAD_NAME                       31: x
        2304    POP_TOP                         
        2306    LOAD_NAME                       33: z
        2308    POP_TOP                         
        2310    LOAD_NAME                       21: n
        2312    POP_TOP                         
        2314    LOAD_NAME                       29: v
        2316    POP_TOP                         
        2318    LOAD_NAME                       29: v
        2320    POP_TOP                         
        2322    LOAD_NAME                       16: i
        2324    POP_TOP                         
        2326    LOAD_NAME                       17: j
        2328    POP_TOP                         
        2330    LOAD_NAME                       18: k
        2332    POP_TOP                         
        2334    LOAD_NAME                       23: p
        2336    POP_TOP                         
        2338    LOAD_NAME                       12: e
        2340    POP_TOP                         
        2342    LOAD_NAME                       10: c
        2344    POP_TOP                         
        2346    LOAD_NAME                       13: f
        2348    POP_TOP                         
        2350    LOAD_NAME                       14: g
        2352    POP_TOP                         
        2354    LOAD_NAME                       11: d
        2356    POP_TOP                         
        2358    LOAD_NAME                       9: b
        2360    POP_TOP                         
        2362    LOAD_NAME                       30: w
        2364    POP_TOP                         
        2366    LOAD_NAME                       25: r
        2368    POP_TOP                         
        2370    LOAD_NAME                       18: k
        2372    POP_TOP                         
        2374    LOAD_NAME                       20: m
        2376    POP_TOP                         
        2378    LOAD_NAME                       14: g
        2380    POP_TOP                         
        2382    LOAD_NAME                       17: j
        2384    POP_TOP                         
        2386    LOAD_NAME                       16: i
        2388    POP_TOP                         
        2390    LOAD_NAME                       21: n
        2392    POP_TOP                         
        2394    LOAD_NAME                       26: s
        2396    POP_TOP                         
        2398    LOAD_NAME                       19: l
        2400    POP_TOP                         
        2402    LOAD_NAME                       28: u
        2404    POP_TOP                         
        2406    LOAD_NAME                       8: a
        2408    POP_TOP                         
        2410    LOAD_NAME                       15: h
        2412    POP_TOP                         
        2414    LOAD_NAME                       33: z
        2416    POP_TOP                         
        2418    LOAD_NAME                       32: y
        2420    POP_TOP                         
        2422    LOAD_NAME                       13: f
        2424    POP_TOP                         
        2426    LOAD_NAME                       10: c
        2428    POP_TOP                         
        2430    LOAD_NAME                       18: k
        2432    POP_TOP                         
        2434    LOAD_NAME                       32: y
        2436    POP_TOP                         
        2438    LOAD_NAME                       18: k
        2440    POP_TOP                         
        2442    LOAD_NAME                       14: g
        2444    POP_TOP                         
        2446    LOAD_NAME                       18: k
        2448    POP_TOP                         
        2450    LOAD_NAME                       30: w
        2452    POP_TOP                         
        2454    LOAD_NAME                       19: l
        2456    POP_TOP                         
        2458    LOAD_NAME                       20: m
        2460    POP_TOP                         
        2462    LOAD_NAME                       25: r
        2464    POP_TOP                         
        2466    LOAD_NAME                       15: h
        2468    POP_TOP                         
        2470    LOAD_NAME                       25: r
        2472    POP_TOP                         
        2474    LOAD_NAME                       28: u
        2476    POP_TOP                         
        2478    LOAD_NAME                       9: b
        2480    POP_TOP                         
        2482    LOAD_NAME                       17: j
        2484    POP_TOP                         
        2486    LOAD_NAME                       32: y
        2488    POP_TOP                         
        2490    LOAD_NAME                       13: f
        2492    POP_TOP                         
        2494    LOAD_NAME                       20: m
        2496    POP_TOP                         
        2498    LOAD_NAME                       13: f
        2500    POP_TOP                         
        2502    LOAD_NAME                       27: t
        2504    POP_TOP                         
        2506    LOAD_NAME                       19: l
        2508    POP_TOP                         
        2510    LOAD_NAME                       8: a
        2512    POP_TOP                         
        2514    LOAD_NAME                       13: f
        2516    POP_TOP                         
        2518    LOAD_NAME                       28: u
        2520    POP_TOP                         
        2522    LOAD_NAME                       17: j
        2524    POP_TOP                         
        2526    LOAD_NAME                       20: m
        2528    POP_TOP                         
        2530    LOAD_NAME                       9: b
        2532    POP_TOP                         
        2534    LOAD_NAME                       16: i
        2536    POP_TOP                         
        2538    LOAD_NAME                       17: j
        2540    POP_TOP                         
        2542    LOAD_NAME                       29: v
        2544    POP_TOP                         
        2546    LOAD_NAME                       30: w
        2548    POP_TOP                         
        2550    LOAD_NAME                       22: o
        2552    POP_TOP                         
        2554    LOAD_NAME                       19: l
        2556    POP_TOP                         
        2558    LOAD_NAME                       30: w
        2560    POP_TOP                         
        2562    LOAD_NAME                       23: p
        2564    POP_TOP                         
        2566    LOAD_NAME                       28: u
        2568    POP_TOP                         
        2570    LOAD_NAME                       8: a
        2572    POP_TOP                         
        2574    LOAD_NAME                       32: y
        2576    POP_TOP                         
        2578    LOAD_NAME                       32: y
        2580    POP_TOP                         
        2582    LOAD_NAME                       31: x
        2584    POP_TOP                         
        2586    LOAD_NAME                       32: y
        2588    POP_TOP                         
        2590    LOAD_NAME                       9: b
        2592    POP_TOP                         
        2594    LOAD_NAME                       11: d
        2596    POP_TOP                         
        2598    LOAD_NAME                       22: o
        2600    POP_TOP                         
        2602    LOAD_NAME                       19: l
        2604    POP_TOP                         
        2606    LOAD_NAME                       20: m
        2608    POP_TOP                         
        2610    LOAD_NAME                       13: f
        2612    POP_TOP                         
        2614    LOAD_NAME                       24: q
        2616    POP_TOP                         
        2618    LOAD_NAME                       28: u
        2620    POP_TOP                         
        2622    LOAD_NAME                       19: l
        2624    POP_TOP                         
        2626    LOAD_NAME                       11: d
        2628    POP_TOP                         
        2630    LOAD_NAME                       31: x
        2632    POP_TOP                         
        2634    LOAD_NAME                       13: f
        2636    POP_TOP                         
        2638    LOAD_NAME                       20: m
        2640    POP_TOP                         
        2642    LOAD_NAME                       29: v
        2644    POP_TOP                         
        2646    LOAD_NAME                       31: x
        2648    POP_TOP                         
        2650    LOAD_NAME                       9: b
        2652    POP_TOP                         
        2654    LOAD_NAME                       33: z
        2656    POP_TOP                         
        2658    LOAD_NAME                       19: l
        2660    POP_TOP                         
        2662    LOAD_NAME                       16: i
        2664    POP_TOP                         
        2666    LOAD_NAME                       30: w
        2668    POP_TOP                         
        2670    LOAD_NAME                       16: i
        2672    POP_TOP                         
        2674    LOAD_NAME                       31: x
        2676    POP_TOP                         
        2678    LOAD_NAME                       12: e
        2680    POP_TOP                         
        2682    LOAD_NAME                       26: s
        2684    POP_TOP                         
        2686    LOAD_NAME                       23: p
        2688    POP_TOP                         
        2690    LOAD_NAME                       21: n
        2692    POP_TOP                         
        2694    LOAD_NAME                       33: z
        2696    POP_TOP                         
        2698    LOAD_NAME                       8: a
        2700    POP_TOP                         
        2702    LOAD_NAME                       31: x
        2704    POP_TOP                         
        2706    LOAD_NAME                       17: j
        2708    POP_TOP                         
        2710    LOAD_NAME                       32: y
        2712    POP_TOP                         
        2714    LOAD_NAME                       25: r
        2716    POP_TOP                         
        2718    LOAD_NAME                       20: m
        2720    POP_TOP                         
        2722    LOAD_NAME                       25: r
        2724    POP_TOP                         
        2726    LOAD_NAME                       15: h
        2728    POP_TOP                         
        2730    LOAD_NAME                       13: f
        2732    POP_TOP                         
        2734    LOAD_NAME                       15: h
        2736    POP_TOP                         
        2738    LOAD_NAME                       22: o
        2740    POP_TOP                         
        2742    LOAD_NAME                       33: z
        2744    POP_TOP                         
        2746    LOAD_NAME                       16: i
        2748    POP_TOP                         
        2750    LOAD_NAME                       33: z
        2752    POP_TOP                         
        2754    LOAD_NAME                       14: g
        2756    POP_TOP                         
        2758    LOAD_NAME                       13: f
        2760    POP_TOP                         
        2762    LOAD_NAME                       29: v
        2764    POP_TOP                         
        2766    LOAD_NAME                       8: a
        2768    POP_TOP                         
        2770    LOAD_NAME                       21: n
        2772    POP_TOP                         
        2774    RETURN_CONST                    14: None
        2776    PUSH_EXC_INFO                   
        2778    LOAD_NAME                       5: ImportError
        2780    CHECK_EXC_MATCH                 
        2782    POP_JUMP_IF_FALSE               19 (to 2822)
        2786    POP_TOP                         
        2788    LOAD_NAME                       6: print
        2790    PUSH_NULL                       
        2792    LOAD_CONST                      3: 'run `pip install pycryptodome` to be able to play this challenge'
        2794    CALL                            1
        2802    POP_TOP                         
        2804    LOAD_NAME                       7: exit
        2806    PUSH_NULL                       
        2808    CALL                            0
        2816    POP_TOP                         
        2818    POP_EXCEPT                      
        2820    JUMP_BACKWARD_NO_INTERRUPT      1396 (to 32)
        2824    RERAISE                         0
        2826    COPY                            3
        2828    POP_EXCEPT                      
        2830    RERAISE                         1
